[
  {},
  {
    "username": "daniel2310dk",
    "email": "danieldk2310@gmail.com",
    "password": "$2b$10$yanDt8afgHQ2CXfvCiMKSeIXBKWTTXmqumNMcx7TiqMAahGTBsjK."
  },
  {
    "username": "booster",
    "email": "brormand@hotmail.dk",
    "password": "$2b$10$z/vzs9gBG0RtPIb4YFSul.kHFUwj0FhDJqPWrLbMjnICFOQ0IE0Gi"
  },
  {
    "username": "anton",
    "email": "anton123@gmail.com",
    "password": "$2b$10$PGVGKQrh5IwFrVwz2bDTROSn3JV6cxH9WNjKiypywzjgiJ3j.t/uO"
  },
  {
    "username": "kat",
    "email": "kat.email@gmail.com",
    "password": "$2b$10$nbL8iVG4yiHobm4dFWnwcOOCobgv116lTC34uVpXhphyC/.mrBnJq"
  },
  {
    "username": "Magda",
    "email": "magda@gmail.com",
    "password": "$2b$10$roxXfj7CDoGlwwhLUyohROzkenRHxb.6a3l6yVUAq6GC/5L9Hf2Vi"
  },
  {
    "username": "anton1",
    "email": "anton@gmail.com",
    "password": "$2b$10$nwrZVyDWQgg9j/2USdmwpenYUB/MEC28y/RkUUFx7313g.m.8ZArW"
  },
  {
    "username": "anni",
    "email": "anton1234@gmail.com",
    "password": "$2b$10$rMLg9ggWEtudRiowzuAPKujBdSjfWpndt9stX/8LmhArihOdXvCpG"
  },
  {
    "username": "Malthe3",
    "email": "maltheandreasen1@gmail.com",
    "password": "$2b$10$DgSI7mZh2VVUGZMZKE7nD.4YaploDQW58kgxPTnjlRagzbpanJfi."
  },
  {
    "username": "kat123456",
    "email": "pik@gmail.com",
    "password": "$2b$10$VXUlsavrx1AbQfCRO3mZe.G5PtDNxXr6xcNayN5nsNS7jPbpzOW8W"
  }
]